django_oauth2-5.0.dist-info/licenses/LICENSE
provider/__init__.py
provider/constants.py
provider/forms.py
provider/models.py
provider/scope.py
provider/sphinx.py
provider/urls.py
provider/utils.py
provider/views.py
provider/compat/__init__.py
provider/oauth2/__init__.py
provider/oauth2/admin.py
provider/oauth2/apps.py
provider/oauth2/backends.py
provider/oauth2/forms.py
provider/oauth2/middleware.py
provider/oauth2/mixins.py
provider/oauth2/models.py
provider/oauth2/signals.py
provider/oauth2/urls.py
provider/oauth2/views.py
provider/oauth2/fixtures/test_oauth2.json
provider/oauth2/management/__init__.py
provider/oauth2/management/commands/__init__.py
provider/oauth2/management/commands/oauth2_migrate_hashed_tokens.py
provider/oauth2/migrations/0001_initial.py
provider/oauth2/migrations/0002_fix_scope_size.py
provider/oauth2/migrations/0003_public_client_options.py
provider/oauth2/migrations/0004_awsaccount.py
provider/oauth2/migrations/0005_pkce.py
provider/oauth2/migrations/0006_clientsecrets.py
provider/oauth2/migrations/0007_secret_tokens.py
provider/oauth2/migrations/__init__.py
provider/oauth2/tests/__init__.py
provider/oauth2/tests/test_middleware.py
provider/oauth2/tests/test_models.py
provider/oauth2/tests/test_views.py
provider/oauth2/tests/urls.py
provider/templates/provider/authorize.html
provider/templatetags/__init__.py
provider/templatetags/scope.py
provider/tests/__init__.py
provider/tests/test_utils.py
django_oauth2-5.0.dist-info/METADATA
django_oauth2-5.0.dist-info/WHEEL
django_oauth2-5.0.dist-info/top_level.txt
django_oauth2-5.0.dist-info/RECORD
