Metadata-Version: 2.4
Name: django-oauth2
Version: 5.0
Summary: Provide OAuth2 access to your app (fork of django-oauth2-provider)
Maintainer-email: Shaun Kruger <shaun.kruger@gmail.com>
Project-URL: Homepage, https://github.com/stormsherpa/django-oauth2-provider
Classifier: Environment :: Web Environment
Classifier: Intended Audience :: Developers
Classifier: Operating System :: OS Independent
Classifier: Programming Language :: Python
Classifier: Framework :: Django
Requires-Python: >=3.8
License-File: LICENSE
Requires-Dist: shortuuid>=1.0.11
Requires-Dist: sqlparse>=0.4.3
Dynamic: license-file
